mosek/__init__.py
mosek/_msk.cpython-310-x86_64-linux-gnu.so
mosek/_msk.cpython-311-x86_64-linux-gnu.so
mosek/_msk.cpython-312-x86_64-linux-gnu.so
mosek/_msk.cpython-313-x86_64-linux-gnu.so
mosek/_msk.cpython-314-x86_64-linux-gnu.so
mosek/_msk.cpython-39-x86_64-linux-gnu.so
mosek/libmosek64.so.11.1
mosek/libtbb.so.12
mosek/fusion/Utils.py
mosek/fusion/__init__.py
mosek/fusion/pythonic.py
mosek/fusion/impl/__init__.py
mosek/fusion/impl/_implementation.py
mosek/fusion/impl/fragments.cpython-310-x86_64-linux-gnu.so
mosek/fusion/impl/fragments.cpython-311-x86_64-linux-gnu.so
mosek/fusion/impl/fragments.cpython-312-x86_64-linux-gnu.so
mosek/fusion/impl/fragments.cpython-313-x86_64-linux-gnu.so
mosek/fusion/impl/fragments.cpython-314-x86_64-linux-gnu.so
mosek/fusion/impl/fragments.cpython-39-x86_64-linux-gnu.so
mosek-11.1.3.dist-info/METADATA
mosek-11.1.3.dist-info/WHEEL
mosek-11.1.3.dist-info/top_level.txt
mosek-11.1.3.dist-info/RECORD
