Metadata-Version: 2.4
Name: Mosek
Version: 11.1.3
Summary: Python API for Mosek
Author-email: Mosek ApS <support@mosek.com>
License: https://mosek.com/products/license-agreement
Project-URL: HOME, https://mosek.com
Requires-Python: <3.15,>=3.9
Requires-Dist: numpy
